{"ApprovalTime": "2016-03-09T23:40:27Z", "AutoApprovalTime": "2016-03-09T23:39:19Z", "AssignmentId": "3ITXP059PWJHUJK9EXD59WRN174SJE", "WorkerId": "anon47", "answers": {"data": {"num_errors": [0, 0, 0, 0, 0, 0, 0, 0, 0, 0, 0, 0, 0, 0, 0, 0, 0, 0, 0, 0, 0, 0, 0, 0, 0, 0, 0, 0, 0, 0, 0, 0, 0], "rating": ["8", "7", "8", "8", "8", "8", "9", "6", "7", "9", "7", "9", "8", "7", "5", "9", "9", "9", "9", "7", "5", "8", "5", "7", "8", "7", "6", "9", "5", "7", "7", "5", "9"], "window_height": [16, 16, 16, 16, 16, 16, 16, 16, 16, 16, 16, 16, 16, 16, 16, 16, 16, 16, 16, 16, 16, 16, 16, 16, 16, 16, 16, 16, 16, 16, 16, 16, 16], "gender": ["male"], "age": ["30-39"], "expt_aim": [""], "face": [0, 20, 30, 20, 40, 50, 60, 10, 40, 100, 60, 100, 70, 30, 0, 90, 70, 90, 80, 50, 0, 50, 10, 40, 80, 70, 30, 100, 20, 80, 60, 10, 90], "expt_gen": [""], "elapsed_ms": [6988, 908925, 3563, 2088, 3870, 2450, 2043, 2156, 2110, 3048, 1571, 2298, 1992, 2539, 2459, 2681, 2572, 3918, 3102, 1607, 2566, 2586, 2224, 5285, 2207, 2278, 2029, 2442, 2255, 2273, 3145, 1834, 2107], "race": ["other"], "user_agent": ["Mozilla/5.0 (Macintosh; Intel Mac OS X 10.11; rv:44.0) Gecko/20100101 Firefox/44.0"], "type": ["trustworthy"], "education": ["someCollege"], "window_width": [1310, 1324, 1324, 1324, 1324, 1324, 1324, 1324, 1324, 1324, 1324, 1324, 1324, 1324, 1324, 1324, 1324, 1324, 1324, 1324, 1324, 1324, 1324, 1324, 1324, 1324, 1324, 1324, 1324, 1324, 1324, 1324, 1324]}}, "AcceptTime": "2016-03-09T23:16:59Z", "HITId": "3CESM1J3EI3VQLOIOGOG8XTHB2P6WZ", "Assignment": "", "AssignmentStatus": "Approved", "SubmitTime": "2016-03-09T23:34:19Z"}